turing/__init__.py
turing/_base_types.py
turing/ensembler.py
turing/ensembler_image.py
turing/mounted_mlp_secret.py
turing/project.py
turing/session.py
turing/version.py
turing/batch/__init__.py
turing/batch/job.py
turing/batch/config/__init__.py
turing/batch/config/config.py
turing/batch/config/sink.py
turing/batch/config/source.py
turing/generated/__init__.py
turing/generated/api_client.py
turing/generated/configuration.py
turing/generated/exceptions.py
turing/generated/model_utils.py
turing/generated/rest.py
turing/generated/api/__init__.py
turing/generated/api/ensembler_api.py
turing/generated/api/ensembler_images_api.py
turing/generated/api/ensembling_job_api.py
turing/generated/api/project_api.py
turing/generated/api/router_api.py
turing/generated/apis/__init__.py
turing/generated/model/__init__.py
turing/generated/model/autoscaling_policy.py
turing/generated/model/big_query_config.py
turing/generated/model/big_query_dataset.py
turing/generated/model/big_query_dataset_all_of.py
turing/generated/model/big_query_dataset_config.py
turing/generated/model/big_query_sink.py
turing/generated/model/big_query_sink_all_of.py
turing/generated/model/big_query_sink_config.py
turing/generated/model/build_ensembler_image_request.py
turing/generated/model/dataset.py
turing/generated/model/default_traffic_rule.py
turing/generated/model/enricher.py
turing/generated/model/ensembler.py
turing/generated/model/ensembler_config.py
turing/generated/model/ensembler_config_kind.py
turing/generated/model/ensembler_docker_config.py
turing/generated/model/ensembler_id.py
turing/generated/model/ensembler_image.py
turing/generated/model/ensembler_image_runner_type.py
turing/generated/model/ensembler_images.py
turing/generated/model/ensembler_infra_config.py
turing/generated/model/ensembler_job_status.py
turing/generated/model/ensembler_pyfunc_config.py
turing/generated/model/ensembler_standard_config.py
turing/generated/model/ensembler_standard_config_experiment_mappings.py
turing_sdk-0.16.0.post2.dist-info/METADATA
turing_sdk-0.16.0.post2.dist-info/WHEEL
turing_sdk-0.16.0.post2.dist-info/top_level.txt
turing_sdk-0.16.0.post2.dist-info/RECORD
