Metadata-Version: 2.1
Name: turing-sdk
Version: 0.16.0.post2
Requires-Python: >=3.8,<3.11
Requires-Dist: cloudpickle==2.0.0
Requires-Dist: deprecation==2.1.0
Requires-Dist: fire
Requires-Dist: google-cloud-storage>=1.19.0
Requires-Dist: mlflow<2.0.0,>=1.26.1
Requires-Dist: pandas
Requires-Dist: protobuf<5.0.0,>=3.12.0
Requires-Dist: python-dateutil>=2.5.3
Requires-Dist: requests
Requires-Dist: urllib3>=1.25.3
Requires-Dist: caraml-auth-google==0.0.0.post9
Requires-Dist: PyPrind>=2.11.2
Requires-Dist: numpy>=1.26.0
Provides-Extra: dev
Requires-Dist: black==22.6.0; extra == "dev"
Requires-Dist: setuptools<75,>=21.0.0; extra == "dev"
Requires-Dist: wheel; extra == "dev"
Requires-Dist: twine; extra == "dev"
Requires-Dist: pytest<=8.1.2; extra == "dev"
Requires-Dist: pytest-cov; extra == "dev"
Requires-Dist: urllib3-mock>=0.3.3; extra == "dev"
Requires-Dist: caraml-upi-protos; extra == "dev"
Requires-Dist: grpcio-reflection; extra == "dev"
